shutup/__init__.py
shutup-0.2.0.dist-info/WHEEL
shutup-0.2.0.dist-info/METADATA
shutup-0.2.0.dist-info/RECORD
